spannerorm/__init__.py
spannerorm/base_model.py
spannerorm/connection.py
spannerorm/criteria.py
spannerorm/dataType.py
spannerorm/data_parser.py
spannerorm/db_migration.py
spannerorm/executor.py
spannerorm/helper.py
spannerorm/model_json_encoder.py
spannerorm/query_builder.py
spannerorm/relation.py
spannerorm/sample_migration.py
spannerorm/spanner_db.py
spannerorm/spanner_exception.py
spannerorm/transactional.py
spannerorm-0.1.17.dist-info/METADATA
spannerorm-0.1.17.dist-info/RECORD
spannerorm-0.1.17.dist-info/WHEEL
spannerorm-0.1.17.dist-info/top_level.txt
