Metadata-Version: 2.1
Name: spannerorm
Version: 0.1.17
Summary: ORM for cloud spanner
Home-page: https://github.com/leapfrogtechnology/spanner-orm
Author: Sanish Maharjan
Author-email: sanishmaharjan@lftechnology.com
License: UNKNOWN
Platform: UNKNOWN
Classifier: Programming Language :: Python :: 2.7
Classifier: Programming Language :: Python :: 3.6
Classifier: License :: OSI Approved :: MIT License
Classifier: Operating System :: OS Independent
Requires-Dist: flask
Requires-Dist: google-cloud-spanner
